instagram_collector/__init__.py
instagram_collector/brands.py
instagram_collector/comments.py
instagram_collector/constants.py
instagram_collector/dynamo_helper.py
instagram_collector/dynamodb.py
instagram_collector/hashtag.py
instagram_collector/post_recent.py
instagram_collector/profile.py
instagram_collector/reels_recent.py
instagram_collector/tagged.py
instagram_collector/utils.py
instagram_collector-0.0.9.dist-info/licenses/LICENSE
tests/__init__.py
tests/test_hashtag.py
instagram_collector-0.0.9.dist-info/METADATA
instagram_collector-0.0.9.dist-info/WHEEL
instagram_collector-0.0.9.dist-info/top_level.txt
instagram_collector-0.0.9.dist-info/RECORD
