Metadata-Version: 2.4
Name: instagram-collector
Version: 0.0.9
Summary: A Python library for collecting Instagram data including hashtag posts, tagged posts, brand posts, and comments
Home-page: https://github.com/yourusername/instagram-collector
Author: Hoang Vu
Author-email: hoangvu@example.com
Classifier: Programming Language :: Python :: 3
Classifier: License :: OSI Approved :: MIT License
Classifier: Operating System :: OS Independent
Requires-Python: >=3.7
License-File: LICENSE
Requires-Dist: requests>=2.25.1
Requires-Dist: pandas>=1.2.0
Requires-Dist: numpy>=1.19.0
Requires-Dist: python-dotenv>=0.19.0
Requires-Dist: pytz>=2021.1
Dynamic: author
Dynamic: author-email
Dynamic: classifier
Dynamic: description
Dynamic: description-content-type
Dynamic: home-page
Dynamic: license-file
Dynamic: requires-dist
Dynamic: requires-python
Dynamic: summary
